mtl/__init__.py
mtl/attribute.py
mtl/tags.py
mtl/css/__init__.py
mtlhtml-1.0.dist-info/LICENSE.md
mtlhtml-1.0.dist-info/METADATA
mtlhtml-1.0.dist-info/WHEEL
mtlhtml-1.0.dist-info/top_level.txt
mtlhtml-1.0.dist-info/RECORD
