Metadata-Version: 2.1
Name: mtlhtml
Version: 1.0
Summary: A tool that help you to write HTML in Python
Home-page: https://github.com/WeAreInSpace/MTL
Author: WeAreInSpace
Author-email: weareinspace.net@gmail.com
License: MIT
Keywords: html in python website ssg
License-File: LICENSE.md
